{
    "authors": [
        {
            "name": "Kitware",
            "slug": "kitware"
        }
    ],
    "date": "June 24, 2014",
    "id": "11821",
    "slug": "adapting-video-image-isr-to-a2ad-talk-at-next-generation-isr",
    "tags": [
        {
            "name": "Company News",
            "slug": "company-news"
        },
        {
            "name": "Computer Vision",
            "slug": "computer-vision"
        },
        {
            "name": "Press Releases",
            "slug": "press"
        }
    ],
    "title": "‘Adapting Video & Image ISR to A2AD’ Talk at Next Generation ISR"
}