{
    "authors": [
        {
            "name": "Kitware",
            "slug": "kitware"
        }
    ],
    "date": "May 7, 2013",
    "id": "11887",
    "slug": "kitware-to-enhance-the-visualization-toolkit-vtk-to-accelerate-community-driven-medical-innovation",
    "tags": [
        {
            "name": "Company News",
            "slug": "company-news"
        },
        {
            "name": "Medical Imaging",
            "slug": "medical-imaging"
        },
        {
            "name": "ParaView",
            "slug": "paraview"
        },
        {
            "name": "Press Releases",
            "slug": "press"
        },
        {
            "name": "Scientific Visualization",
            "slug": "scientific-visualization"
        },
        {
            "name": "VTK",
            "slug": "vtk"
        }
    ],
    "title": "Kitware to Enhance the Visualization Toolkit (VTK) to Accelerate Community-Driven Medical Innovation"
}