{
    "authors": [
        {
            "name": "Kitware",
            "slug": "kitware"
        }
    ],
    "date": "November 27, 2012",
    "id": "11905",
    "slug": "kitware-receives-darpa-funding-to-develop-a-visualization-design-environment",
    "tags": [
        {
            "name": "Company News",
            "slug": "company-news"
        },
        {
            "name": "Customer Spotlight",
            "slug": "customer-spotlight"
        },
        {
            "name": "Press Releases",
            "slug": "press"
        },
        {
            "name": "Scientific Visualization",
            "slug": "scientific-visualization"
        },
        {
            "name": "VTK",
            "slug": "vtk"
        }
    ],
    "title": "Kitware Receives DARPA Funding to Develop a Visualization Design Environment"
}