{
    "authors": [
        {
            "name": "Kitware",
            "slug": "kitware"
        }
    ],
    "date": "April 20, 2011",
    "id": "12000",
    "slug": "kitware-announces-itk-course-in-lyon-france",
    "tags": [
        {
            "name": "Company News",
            "slug": "company-news"
        },
        {
            "name": "ITK",
            "slug": "itk"
        },
        {
            "name": "Press Releases",
            "slug": "press"
        }
    ],
    "title": "Kitware Announces ITK Course in Lyon, France"
}