{
    "authors": [
        {
            "name": "Kitware",
            "slug": "kitware"
        }
    ],
    "date": "October 27, 2010",
    "id": "12020",
    "slug": "kitware-the-na-mic-community-announce-alpha-release-of-3d-slicer-4-0",
    "tags": [
        {
            "name": "CDash",
            "slug": "cdash"
        },
        {
            "name": "CMake",
            "slug": "cmake"
        },
        {
            "name": "Company News",
            "slug": "company-news"
        },
        {
            "name": "ITK",
            "slug": "itk"
        },
        {
            "name": "Medical Imaging",
            "slug": "medical-imaging"
        },
        {
            "name": "MIDAS",
            "slug": "midas"
        },
        {
            "name": "Press Releases",
            "slug": "press"
        },
        {
            "name": "VTK",
            "slug": "vtk"
        }
    ],
    "title": "Kitware & the NA-MIC Community Announce Alpha Release of 3D Slicer 4.0"
}