{
    "authors": [
        {
            "name": "Joachim Pouderoux",
            "slug": "joachim-pouderoux"
        }
    ],
    "date": "December 17, 2015",
    "id": "12257",
    "slug": "introducing-some-new-paraview-5-0-features",
    "tags": [
        {
            "name": "Company News",
            "slug": "company-news"
        },
        {
            "name": "ParaView",
            "slug": "paraview"
        },
        {
            "name": "Scientific Visualization",
            "slug": "scientific-visualization"
        }
    ],
    "title": "Introducing some new ParaView 5.0 features"
}