{
    "authors": [
        {
            "name": "Robert Maynard",
            "slug": "robert-maynard"
        }
    ],
    "date": "October 6, 2015",
    "id": "12293",
    "slug": "cmake-3-4-0-rc1-is-now-ready",
    "tags": [
        {
            "name": "CMake",
            "slug": "cmake"
        },
        {
            "name": "Company News",
            "slug": "company-news"
        },
        {
            "name": "Software Process",
            "slug": "software-process"
        }
    ],
    "title": "CMake 3.4.0-rc1 is now ready!"
}