{
    "authors": [
        {
            "name": "Sandy McKenzie",
            "slug": "sandy-mckenzie"
        }
    ],
    "date": "March 20, 2015",
    "id": "12395",
    "slug": "continuous-collision-detection-for-deformable-solids-with-topological-changes",
    "tags": [
        {
            "name": "Company News",
            "slug": "company-news"
        },
        {
            "name": "Medical Imaging",
            "slug": "medical-imaging"
        }
    ],
    "title": "Continuous Collision Detection for Deformable Solids with Topological Changes"
}