{
    "authors": [
        {
            "name": "Marcus D. Hanwell",
            "slug": "marcus-hanwell"
        }
    ],
    "date": "November 7, 2014",
    "id": "12472",
    "slug": "google-summer-of-code-ten-year-reunion",
    "tags": [
        {
            "name": "Open Chemistry",
            "slug": "open-chemistry"
        },
        {
            "name": "Scientific Visualization",
            "slug": "scientific-visualization"
        },
        {
            "name": "VTK",
            "slug": "vtk"
        }
    ],
    "title": "Google Summer of Code Ten Year Reunion"
}