{
    "authors": [
        {
            "name": "Matt McCormick",
            "slug": "matt-mccormick"
        }
    ],
    "date": "April 30, 2014",
    "id": "12569",
    "slug": "itk-sphinx-examples-part-i-credits-via-gitstats",
    "tags": [
        {
            "name": "Data & Analytics",
            "slug": "data-analytics"
        },
        {
            "name": "ITK",
            "slug": "itk"
        },
        {
            "name": "Medical Imaging",
            "slug": "medical-imaging"
        },
        {
            "name": "Software Process",
            "slug": "software-process"
        }
    ],
    "title": "ITK Sphinx Examples Part I: Credits via GitStats"
}