{
    "authors": [
        {
            "name": "Sandy McKenzie",
            "slug": "sandy-mckenzie"
        }
    ],
    "date": "October 14, 2015",
    "id": "13148",
    "slug": "kitware-introduces-resonant-open-source-data-and-analytics",
    "tags": [
        {
            "name": "Data & Analytics",
            "slug": "data-analytics"
        },
        {
            "name": "Kitware Source Quarterly Magazine",
            "slug": "kitware-source"
        },
        {
            "name": "Resonant",
            "slug": "resonant"
        },
        {
            "name": "The Source Issue 35",
            "slug": "the-source-issue-35"
        }
    ],
    "title": "Kitware Introduces Resonant: Open-Source Data and Analytics"
}