{
    "authors": [
        {
            "name": "Sandy McKenzie",
            "slug": "sandy-mckenzie"
        }
    ],
    "date": "January 30, 2015",
    "id": "13163",
    "slug": "kitware-news-5",
    "tags": [
        {
            "name": "Kitware Source Quarterly Magazine",
            "slug": "kitware-source"
        },
        {
            "name": "The Source Issue 32",
            "slug": "the-source-issue-32"
        },
        {
            "name": "The Source Kitware News",
            "slug": "the-source-kitware-news"
        }
    ],
    "title": "Kitware News"
}