{
    "authors": [
        {
            "name": "Sandy McKenzie",
            "slug": "sandy-mckenzie"
        }
    ],
    "date": "July 24, 2014",
    "id": "13175",
    "slug": "kitware-news-7",
    "tags": [
        {
            "name": "Kitware Source Quarterly Magazine",
            "slug": "kitware-source"
        },
        {
            "name": "The Source Issue 30",
            "slug": "the-source-issue-30"
        },
        {
            "name": "The Source Kitware News",
            "slug": "the-source-kitware-news"
        }
    ],
    "title": "Kitware News"
}