{
    "authors": [
        {
            "name": "Sandy McKenzie",
            "slug": "sandy-mckenzie"
        }
    ],
    "date": "April 17, 2014",
    "id": "13182",
    "slug": "cmake-and-the-wolfram-language",
    "tags": [
        {
            "name": "CMake",
            "slug": "cmake"
        },
        {
            "name": "Kitware Source Quarterly Magazine",
            "slug": "kitware-source"
        },
        {
            "name": "Software Process",
            "slug": "software-process"
        },
        {
            "name": "The Source Issue 29",
            "slug": "the-source-issue-29"
        }
    ],
    "title": "CMake and the Wolfram Language"
}