{
    "authors": [
        {
            "name": "Katie Sharkey",
            "slug": "katie-sharkey"
        }
    ],
    "date": "July 15, 2011",
    "id": "13282",
    "slug": "divide-and-conquer",
    "tags": [
        {
            "name": "ITK",
            "slug": "itk"
        },
        {
            "name": "Kitware Source Quarterly Magazine",
            "slug": "kitware-source"
        },
        {
            "name": "The Source Issue 18",
            "slug": "the-source-issue-18"
        }
    ],
    "title": "Divide and Conquer"
}