{
    "authors": [
        {
            "name": "Davide Punzo",
            "slug": "davide-punzo"
        }
    ],
    "date": "July 21, 2016",
    "id": "15231",
    "slug": "introducing-slicerastro-a-visualization-tool-for-hydrogen-in-galaxies",
    "tags": [
        {
            "name": "3D Slicer",
            "slug": "3d-slicer"
        },
        {
            "name": "Kitware Source Quarterly Magazine",
            "slug": "kitware-source"
        },
        {
            "name": "The Source Issue 38",
            "slug": "the-source-issue-38"
        }
    ],
    "title": "Introducing SlicerAstro: A Visualization Tool for Hydrogen in Galaxies"
}