{
    "authors": [
        {
            "name": "Dan Lipsa",
            "slug": "dan-lipsa"
        }
    ],
    "date": "October 31, 2016",
    "id": "16441",
    "slug": "enhancements-to-the-community-atmospheric-model-cam-netcdf-reader",
    "tags": [
        {
            "name": "ParaView",
            "slug": "paraview"
        },
        {
            "name": "VTK",
            "slug": "vtk"
        }
    ],
    "title": "Enhancements to the Community Atmospheric Model (CAM) NetCDF Reader"
}