{
    "authors": [
        {
            "name": "Dan Lipsa",
            "slug": "dan-lipsa"
        }
    ],
    "date": "July 24, 2017",
    "id": "18592",
    "slug": "evenly-spaced-streamlines-2d",
    "tags": [
        {
            "name": "Climate Data Analysis",
            "slug": "climate-data-analysis"
        },
        {
            "name": "ParaView",
            "slug": "paraview"
        },
        {
            "name": "Scientific Visualization",
            "slug": "scientific-visualization"
        },
        {
            "name": "VTK",
            "slug": "vtk"
        }
    ],
    "title": "Evenly Spaced Streamlines 2D"
}